streak/__init__.py
streak/db.py
streak/streak.py
streak_cal-0.3.dist-info/LICENSE
streak_cal-0.3.dist-info/METADATA
streak_cal-0.3.dist-info/WHEEL
streak_cal-0.3.dist-info/entry_points.txt
streak_cal-0.3.dist-info/top_level.txt
streak_cal-0.3.dist-info/RECORD
