Metadata-Version: 2.1
Name: streak-cal
Version: 0.3
Summary: A cli calendar for keeping track of streaks
Home-page: https://github.com/kachaMukabe/streak
Author: Kacha Mukabe
License: UNKNOWN
Platform: UNKNOWN
Classifier: Programming Language :: Python :: 3
Classifier: License :: OSI Approved :: MIT License
Classifier: Operating System :: OS Independent
Requires-Python: >=3.6
Requires-Dist: Click
Requires-Dist: tinydb
Requires-Dist: termcolor
Requires-Dist: colorama
